{
    "Ana Silva": {
        "telefone": "(11) 98765-4321",
        "email": "ana.silva@email.com"
    },
    "Bruno Souza": {
        "telefone": "(21) 99988-7766",
        "email": "bruno.souza@dominio.com"
    },
    "Carla Mendes": {
        "telefone": "(31) 98877-6655",
        "email": "carla.m@empresa.org"
    },
    "Diego Rocha": {
        "telefone": "(47) 99111-2233",
        "email": "diego.rocha@site.net"
    },
    "Elaine Costa": {
        "telefone": "(85) 99223-3445",
        "email": "elaine.costa@email.com"
    },
    "Fábio Lima": {
        "telefone": "(62) 99654-7788",
        "email": "fabio.lima@empresa.com"
    },
    "Gabriela Alves": {
        "telefone": "(19) 99876-1122",
        "email": "gabriela.a@contato.com"
    },
    "Henrique Duarte": {
        "telefone": "(27) 99123-4455",
        "email": "henrique.duarte@provedor.com"
    },
    "Isabela Martins": {
        "telefone": "(41) 99345-6677",
        "email": "isabela.martins@email.org"
    },
    "João Pedro": {
        "telefone": "(51) 98765-8899",
        "email": "joao.pedro@site.com"
    },
    "Larissa Nogueira": {
        "telefone": "(34) 99456-7788",
        "email": "larissa.ngr@dominio.org"
    },
    "Marcelo Tavares": {
        "telefone": "(13) 99001-2233",
        "email": "marcelo.tavares@empresa.net"
    }
}